{
  "city_code": "zh",
  "city_name": "珠海",
  "province": "广东",
  "scraped_at": "2026-07-09T11:59:46",
  "districts": [
    {
      "name": "斗门区",
      "code": "DM",
      "city_code": "zh"
    },
    {
      "name": "金湾区",
      "code": "JW",
      "city_code": "zh"
    },
    {
      "name": "香洲区",
      "code": "XZ",
      "city_code": "zh"
    },
    {
      "name": "高新区",
      "code": "G1",
      "city_code": "zh"
    },
    {
      "name": "高栏港区",
      "code": "J1",
      "city_code": "zh"
    }
  ],
  "price_timeline": {
    "city": [
      {
        "year_month": "2025-07",
        "supply_price": 13266,
        "attention_price": null,
        "value_price": 13266,
        "sample_count": 1786
      },
      {
        "year_month": "2025-08",
        "supply_price": 13421,
        "attention_price": null,
        "value_price": 13421,
        "sample_count": 1764
      },
      {
        "year_month": "2025-09",
        "supply_price": 13196,
        "attention_price": 10974,
        "value_price": 13196,
        "sample_count": 1006
      },
      {
        "year_month": "2025-10",
        "supply_price": 12368,
        "attention_price": 16623,
        "value_price": 12368,
        "sample_count": 707
      },
      {
        "year_month": "2025-11",
        "supply_price": 12108,
        "attention_price": 18094,
        "value_price": 12108,
        "sample_count": 843
      },
      {
        "year_month": "2025-12",
        "supply_price": 12332,
        "attention_price": 26080,
        "value_price": 12332,
        "sample_count": 933
      },
      {
        "year_month": "2026-01",
        "supply_price": 12004,
        "attention_price": 17490,
        "value_price": 12004,
        "sample_count": 872
      },
      {
        "year_month": "2026-02",
        "supply_price": 11925,
        "attention_price": 14291,
        "value_price": 11925,
        "sample_count": 3447
      },
      {
        "year_month": "2026-03",
        "supply_price": 12526,
        "attention_price": 14101,
        "value_price": 12526,
        "sample_count": 1761
      },
      {
        "year_month": "2026-04",
        "supply_price": 12304,
        "attention_price": 8033,
        "value_price": 12304,
        "sample_count": 1489
      },
      {
        "year_month": "2026-05",
        "supply_price": 12256,
        "attention_price": 8138,
        "value_price": 12256,
        "sample_count": 1023
      },
      {
        "year_month": "2026-06",
        "supply_price": 12315,
        "attention_price": null,
        "value_price": 12315,
        "sample_count": 794
      },
      {
        "year_month": "2026-07",
        "supply_price": 12341,
        "attention_price": 6706,
        "value_price": 12341,
        "sample_count": 799
      }
    ],
    "districts": {
      "DM": [
        {
          "year_month": "2025-07",
          "supply_price": 7289,
          "attention_price": null,
          "value_price": 7289,
          "sample_count": 286
        },
        {
          "year_month": "2025-08",
          "supply_price": 6949,
          "attention_price": null,
          "value_price": 6949,
          "sample_count": 242
        },
        {
          "year_month": "2025-09",
          "supply_price": 7015,
          "attention_price": 8142,
          "value_price": 7015,
          "sample_count": 187
        },
        {
          "year_month": "2025-10",
          "supply_price": 6841,
          "attention_price": null,
          "value_price": 6841,
          "sample_count": 153
        },
        {
          "year_month": "2025-11",
          "supply_price": 6811,
          "attention_price": null,
          "value_price": 6811,
          "sample_count": 228
        },
        {
          "year_month": "2025-12",
          "supply_price": 6835,
          "attention_price": null,
          "value_price": 6835,
          "sample_count": 200
        },
        {
          "year_month": "2026-01",
          "supply_price": 6871,
          "attention_price": 8275,
          "value_price": 6871,
          "sample_count": 144
        },
        {
          "year_month": "2026-02",
          "supply_price": 6820,
          "attention_price": 7746,
          "value_price": 6820,
          "sample_count": 376
        },
        {
          "year_month": "2026-03",
          "supply_price": 6837,
          "attention_price": 6278,
          "value_price": 6837,
          "sample_count": 298
        },
        {
          "year_month": "2026-04",
          "supply_price": 6867,
          "attention_price": null,
          "value_price": 6867,
          "sample_count": 250
        },
        {
          "year_month": "2026-05",
          "supply_price": 6689,
          "attention_price": null,
          "value_price": 6689,
          "sample_count": 214
        },
        {
          "year_month": "2026-06",
          "supply_price": 6905,
          "attention_price": null,
          "value_price": 6905,
          "sample_count": 163
        },
        {
          "year_month": "2026-07",
          "supply_price": 6879,
          "attention_price": null,
          "value_price": 6879,
          "sample_count": 163
        }
      ],
      "JW": [
        {
          "year_month": "2025-07",
          "supply_price": 8533,
          "attention_price": null,
          "value_price": 8533,
          "sample_count": 195
        },
        {
          "year_month": "2025-08",
          "supply_price": 8807,
          "attention_price": null,
          "value_price": 8807,
          "sample_count": 149
        },
        {
          "year_month": "2025-09",
          "supply_price": 8541,
          "attention_price": 8497,
          "value_price": 8541,
          "sample_count": 87
        },
        {
          "year_month": "2025-10",
          "supply_price": 8080,
          "attention_price": null,
          "value_price": 8080,
          "sample_count": 71
        },
        {
          "year_month": "2025-11",
          "supply_price": 8212,
          "attention_price": 13587,
          "value_price": 8212,
          "sample_count": 87
        },
        {
          "year_month": "2025-12",
          "supply_price": 8044,
          "attention_price": null,
          "value_price": 8044,
          "sample_count": 100
        },
        {
          "year_month": "2026-01",
          "supply_price": 7944,
          "attention_price": null,
          "value_price": 7944,
          "sample_count": 92
        },
        {
          "year_month": "2026-02",
          "supply_price": 8067,
          "attention_price": 9231,
          "value_price": 8067,
          "sample_count": 252
        },
        {
          "year_month": "2026-03",
          "supply_price": 8429,
          "attention_price": 7870,
          "value_price": 8429,
          "sample_count": 236
        },
        {
          "year_month": "2026-04",
          "supply_price": 8022,
          "attention_price": 8033,
          "value_price": 8022,
          "sample_count": 156
        },
        {
          "year_month": "2026-05",
          "supply_price": 8451,
          "attention_price": 8138,
          "value_price": 8451,
          "sample_count": 136
        },
        {
          "year_month": "2026-06",
          "supply_price": 7886,
          "attention_price": null,
          "value_price": 7886,
          "sample_count": 94
        },
        {
          "year_month": "2026-07",
          "supply_price": 8075,
          "attention_price": 6793,
          "value_price": 8075,
          "sample_count": 101
        }
      ],
      "XZ": [
        {
          "year_month": "2025-07",
          "supply_price": 14814,
          "attention_price": null,
          "value_price": 14814,
          "sample_count": 1305
        },
        {
          "year_month": "2025-08",
          "supply_price": 15149,
          "attention_price": null,
          "value_price": 15149,
          "sample_count": 1373
        },
        {
          "year_month": "2025-09",
          "supply_price": 14761,
          "attention_price": 17840,
          "value_price": 14761,
          "sample_count": 732
        },
        {
          "year_month": "2025-10",
          "supply_price": 13955,
          "attention_price": 22359,
          "value_price": 13955,
          "sample_count": 483
        },
        {
          "year_month": "2025-11",
          "supply_price": 13664,
          "attention_price": 21870,
          "value_price": 13664,
          "sample_count": 528
        },
        {
          "year_month": "2025-12",
          "supply_price": 13887,
          "attention_price": 29832,
          "value_price": 13887,
          "sample_count": 633
        },
        {
          "year_month": "2026-01",
          "supply_price": 13564,
          "attention_price": 27609,
          "value_price": 13564,
          "sample_count": 636
        },
        {
          "year_month": "2026-02",
          "supply_price": 13125,
          "attention_price": 22206,
          "value_price": 13125,
          "sample_count": 2819
        },
        {
          "year_month": "2026-03",
          "supply_price": 13918,
          "attention_price": 20910,
          "value_price": 13918,
          "sample_count": 1227
        },
        {
          "year_month": "2026-04",
          "supply_price": 13675,
          "attention_price": null,
          "value_price": 13675,
          "sample_count": 1083
        },
        {
          "year_month": "2026-05",
          "supply_price": 13588,
          "attention_price": null,
          "value_price": 13588,
          "sample_count": 673
        },
        {
          "year_month": "2026-06",
          "supply_price": 13661,
          "attention_price": null,
          "value_price": 13661,
          "sample_count": 537
        },
        {
          "year_month": "2026-07",
          "supply_price": 13687,
          "attention_price": null,
          "value_price": 13687,
          "sample_count": 535
        }
      ],
      "G1": [],
      "J1": []
    }
  },
  "price_distribution": {
    "city": [
      {
        "price_range_low": 0,
        "price_range_high": 5000,
        "percentage": 0.13
      },
      {
        "price_range_low": 5000,
        "price_range_high": 10000,
        "percentage": 16.14
      },
      {
        "price_range_low": 10000,
        "price_range_high": 15000,
        "percentage": 11.71
      },
      {
        "price_range_low": 15000,
        "price_range_high": 20000,
        "percentage": 24.56
      },
      {
        "price_range_low": 20000,
        "price_range_high": 25000,
        "percentage": 22.52
      },
      {
        "price_range_low": 25000,
        "price_range_high": 30000,
        "percentage": 12.37
      },
      {
        "price_range_low": 30000,
        "price_range_high": 35000,
        "percentage": 6.13
      },
      {
        "price_range_low": 35000,
        "price_range_high": 40000,
        "percentage": 2.91
      },
      {
        "price_range_low": 40000,
        "price_range_high": 45000,
        "percentage": 1.39
      },
      {
        "price_range_low": 45000,
        "price_range_high": 50000,
        "percentage": 0.9
      },
      {
        "price_range_low": 50000,
        "price_range_high": 55000,
        "percentage": 0.57
      },
      {
        "price_range_low": 55000,
        "price_range_high": 60000,
        "percentage": 0.23
      },
      {
        "price_range_low": 60000,
        "price_range_high": 65000,
        "percentage": 0.22
      },
      {
        "price_range_low": 65000,
        "price_range_high": 70000,
        "percentage": 0.12
      },
      {
        "price_range_low": 70000,
        "price_range_high": 75000,
        "percentage": 0.03
      },
      {
        "price_range_low": 75000,
        "price_range_high": 80000,
        "percentage": 0.04
      },
      {
        "price_range_low": 80000,
        "price_range_high": 85000,
        "percentage": 0.02
      },
      {
        "price_range_low": 85000,
        "price_range_high": 90000,
        "percentage": 0.02
      },
      {
        "price_range_low": 90000,
        "price_range_high": 95000,
        "percentage": 0.01
      },
      {
        "price_range_low": 95000,
        "price_range_high": 100000,
        "percentage": null
      },
      {
        "price_range_low": 100000,
        "price_range_high": 105000,
        "percentage": null
      }
    ],
    "districts": {
      "DM": [
        {
          "price_range_low": 5500,
          "price_range_high": 6000,
          "percentage": 2.41
        },
        {
          "price_range_low": 6000,
          "price_range_high": 6500,
          "percentage": 7.54
        },
        {
          "price_range_low": 6500,
          "price_range_high": 7000,
          "percentage": 9.89
        },
        {
          "price_range_low": 7000,
          "price_range_high": 7500,
          "percentage": 11.22
        },
        {
          "price_range_low": 7500,
          "price_range_high": 8000,
          "percentage": 10.71
        },
        {
          "price_range_low": 8000,
          "price_range_high": 8500,
          "percentage": 10.2
        },
        {
          "price_range_low": 8500,
          "price_range_high": 9000,
          "percentage": 9.51
        },
        {
          "price_range_low": 9000,
          "price_range_high": 9500,
          "percentage": 7.29
        },
        {
          "price_range_low": 9500,
          "price_range_high": 10000,
          "percentage": 6.21
        },
        {
          "price_range_low": 10000,
          "price_range_high": 10500,
          "percentage": 5.32
        },
        {
          "price_range_low": 10500,
          "price_range_high": 11000,
          "percentage": 4.56
        },
        {
          "price_range_low": 11000,
          "price_range_high": 11500,
          "percentage": 2.66
        },
        {
          "price_range_low": 11500,
          "price_range_high": 12000,
          "percentage": 2.28
        },
        {
          "price_range_low": 12000,
          "price_range_high": 12500,
          "percentage": 2.15
        },
        {
          "price_range_low": 12500,
          "price_range_high": 13000,
          "percentage": 1.9
        },
        {
          "price_range_low": 13000,
          "price_range_high": 13500,
          "percentage": 1.84
        },
        {
          "price_range_low": 13500,
          "price_range_high": 14000,
          "percentage": 1.58
        },
        {
          "price_range_low": 14000,
          "price_range_high": 14500,
          "percentage": 0.95
        },
        {
          "price_range_low": 14500,
          "price_range_high": 15000,
          "percentage": 0.51
        },
        {
          "price_range_low": 15000,
          "price_range_high": 15500,
          "percentage": 0.76
        },
        {
          "price_range_low": 15500,
          "price_range_high": 16000,
          "percentage": 0.51
        }
      ],
      "JW": [
        {
          "price_range_low": 4000,
          "price_range_high": 5000,
          "percentage": 0.19
        },
        {
          "price_range_low": 5000,
          "price_range_high": 6000,
          "percentage": 0.88
        },
        {
          "price_range_low": 6000,
          "price_range_high": 7000,
          "percentage": 3.4
        },
        {
          "price_range_low": 7000,
          "price_range_high": 8000,
          "percentage": 7.49
        },
        {
          "price_range_low": 8000,
          "price_range_high": 9000,
          "percentage": 19.36
        },
        {
          "price_range_low": 9000,
          "price_range_high": 10000,
          "percentage": 14.69
        },
        {
          "price_range_low": 10000,
          "price_range_high": 11000,
          "percentage": 12.16
        },
        {
          "price_range_low": 11000,
          "price_range_high": 12000,
          "percentage": 8.37
        },
        {
          "price_range_low": 12000,
          "price_range_high": 13000,
          "percentage": 5.54
        },
        {
          "price_range_low": 13000,
          "price_range_high": 14000,
          "percentage": 5.35
        },
        {
          "price_range_low": 14000,
          "price_range_high": 15000,
          "percentage": 5.25
        },
        {
          "price_range_low": 15000,
          "price_range_high": 16000,
          "percentage": 4.28
        },
        {
          "price_range_low": 16000,
          "price_range_high": 17000,
          "percentage": 2.63
        },
        {
          "price_range_low": 17000,
          "price_range_high": 18000,
          "percentage": 3.31
        },
        {
          "price_range_low": 18000,
          "price_range_high": 19000,
          "percentage": 1.36
        },
        {
          "price_range_low": 19000,
          "price_range_high": 20000,
          "percentage": 1.17
        },
        {
          "price_range_low": 20000,
          "price_range_high": 21000,
          "percentage": 1.17
        },
        {
          "price_range_low": 21000,
          "price_range_high": 22000,
          "percentage": 1.36
        },
        {
          "price_range_low": 22000,
          "price_range_high": 23000,
          "percentage": 0.88
        },
        {
          "price_range_low": 23000,
          "price_range_high": 24000,
          "percentage": 0.88
        },
        {
          "price_range_low": 24000,
          "price_range_high": 25000,
          "percentage": 0.29
        }
      ],
      "XZ": [
        {
          "price_range_low": 8000,
          "price_range_high": 10000,
          "percentage": 0.07
        },
        {
          "price_range_low": 10000,
          "price_range_high": 12000,
          "percentage": 0.81
        },
        {
          "price_range_low": 12000,
          "price_range_high": 14000,
          "percentage": 2.84
        },
        {
          "price_range_low": 14000,
          "price_range_high": 16000,
          "percentage": 5.85
        },
        {
          "price_range_low": 16000,
          "price_range_high": 18000,
          "percentage": 13.48
        },
        {
          "price_range_low": 18000,
          "price_range_high": 20000,
          "percentage": 14.67
        },
        {
          "price_range_low": 20000,
          "price_range_high": 22000,
          "percentage": 14.09
        },
        {
          "price_range_low": 22000,
          "price_range_high": 24000,
          "percentage": 11.88
        },
        {
          "price_range_low": 24000,
          "price_range_high": 26000,
          "percentage": 9.05
        },
        {
          "price_range_low": 26000,
          "price_range_high": 28000,
          "percentage": 7.08
        },
        {
          "price_range_low": 28000,
          "price_range_high": 30000,
          "percentage": 4.85
        },
        {
          "price_range_low": 30000,
          "price_range_high": 32000,
          "percentage": 3.69
        },
        {
          "price_range_low": 32000,
          "price_range_high": 34000,
          "percentage": 3.28
        },
        {
          "price_range_low": 34000,
          "price_range_high": 36000,
          "percentage": 2.36
        },
        {
          "price_range_low": 36000,
          "price_range_high": 38000,
          "percentage": 1.79
        },
        {
          "price_range_low": 38000,
          "price_range_high": 40000,
          "percentage": 1.11
        },
        {
          "price_range_low": 40000,
          "price_range_high": 42000,
          "percentage": 0.96
        },
        {
          "price_range_low": 42000,
          "price_range_high": 44000,
          "percentage": 0.6
        },
        {
          "price_range_low": 44000,
          "price_range_high": 46000,
          "percentage": 0.68
        },
        {
          "price_range_low": 46000,
          "price_range_high": 48000,
          "percentage": 0.46
        },
        {
          "price_range_low": 48000,
          "price_range_high": 50000,
          "percentage": 0.41
        }
      ],
      "G1": [],
      "J1": []
    }
  }
}